LICENSE
MANIFEST.in
README.md
setup.cfg
setup.py
charsleft/.DS_Store
charsleft/__init__.py
charsleft/admin.py
charsleft/models.py
charsleft/tests.py
charsleft/views.py
charsleft/widgets.py
charsleft/static/charsleft/css/charsleft.css
charsleft/static/charsleft/js/charsleft.js
charsleft/templates/charsleft/widgets/charfield.html
charsleft/templates/charsleft/widgets/textfield.html
django_admin_charsleft.egg-info/PKG-INFO
django_admin_charsleft.egg-info/SOURCES.txt
django_admin_charsleft.egg-info/dependency_links.txt
django_admin_charsleft.egg-info/not-zip-safe
django_admin_charsleft.egg-info/requires.txt
django_admin_charsleft.egg-info/top_level.txt