Metadata-Version: 1.1
Name: django-admin-charsleft
Version: 0.0.5
Summary: Widgets and admin mixin to display remaining characters in django admin.
Home-page: https://github.com/palmbeach-interactive/django-admin-charsleft/
Author: Marc Widmer, Jonas Ohrstrom
Author-email: marc@pbi.io, jonas@pbi.io
License: BSD License
Platform: OS Independent
Classifier: Environment :: Web Environment
Classifier: Framework :: Django
Classifier: Intended Audience :: Developers
Classifier: License :: OSI Approved :: MIT License
Classifier: Operating System :: OS Independent
Classifier: Programming Language :: Python
Classifier: Programming Language :: Python :: 2
Classifier: Programming Language :: Python :: 3
